README.rst
setup.cfg
setup.py
arxiv_cli/__init__.py
arxiv_cli/api.py
arxiv_cli/cli.py
arxiv_cli/config.py
arxiv_cli/core.py
arxiv_cli/errors.py
arxiv_cli/utils.py
arxiv_cli.egg-info/PKG-INFO
arxiv_cli.egg-info/SOURCES.txt
arxiv_cli.egg-info/dependency_links.txt
arxiv_cli.egg-info/entry_points.txt
arxiv_cli.egg-info/not-zip-safe
arxiv_cli.egg-info/requires.txt
arxiv_cli.egg-info/top_level.txt